[
{
  "model": "scraping.city",
  "pk": 1,
  "fields": {
    "name": "Тында",
    "slug": "tynda"
  }
},
{
  "model": "scraping.city",
  "pk": 2,
  "fields": {
    "name": "Хабаровск",
    "slug": "habarovsk"
  }
},
{
  "model": "scraping.city",
  "pk": 4,
  "fields": {
    "name": "Комсомольск-на-Амуре",
    "slug": "komsomolsk-na-amure"
  }
},
{
  "model": "scraping.language",
  "pk": 1,
  "fields": {
    "name": "Питон",
    "slug": "piton"
  }
},
{
  "model": "scraping.language",
  "pk": 2,
  "fields": {
    "name": "Python",
    "slug": "python"
  }
},
{
  "model": "scraping.vacancy",
  "pk": 1,
  "fields": {
    "url": "https://khabarovsk.hh.ru/vacancy/66844910?from=vacancy_search_list&hhtmFrom=vacancy_search_list&query=python",
    "title": "Python разработчик",
    "company": "ООО Совкомбанк Технологии",
    "description": "Требуемый опыт работы: 1–3 года\r\n\r\nПолная занятость, полный день\r\n\r\nПРОЕКТ:\r\n\r\nМы занимаемся разработкой web -сервисов и приложений, как внешних, так и внутренних. Мы постоянно растём и поэтому компания доверяет нам новые бизнес направления. Для backend’а мы используем Python (Django/DRF, asyncio), Oracle/PostgreSQL/MySQL/MariaDB, Redis, Celery, RabbitMQ/Kafka, Minio S3, Graylog. На frontend’е работаем с Vue.js, ReactJS. Стараемся покрывать свой код тестами, т.к. знаем насколько они полезны. В некоторых проектах работаем с Docker/Kubernetes. Ведём базу знаний в Confluence, а статусы и прогресс отражаем в YouTrack.\r\n\r\nОдин из наших основных продуктов – современная многокомпонентная система, предназначенная для управления сетью Почтоматов «Халва» (далее – ПО Почтомат «Халва»), обеспечивающая работу на данный момент около 2000 устройств по всей стране и интегрированная более чем с 10-ю логистическими партнёрами. Основной стек технологий – Python, DRF, PostgreSQL, ReactJS. Наша команда выполняет весь спектр работ по развитию системы: от проработки UI до тестирования и пилотирования.\r\n\r\nЧЕМ ПРЕДСТОИТ ЗАНИМАТЬСЯ:\r\n\r\nРазработка и поддержка собственных систем: бизнес-логика, backend, REST API, интеграция с внешними и внутренними сервисами\r\nКоммуникация с заказчиком по вопросам доработки продукта по необходимости.\r\nТРЕБОВАНИЯ:\r\n\r\nПонимание Agile и его основных принципов;\r\n\r\nОпыт работы с языком программирования Python от 2-х лет;\r\n\r\nХорошее знание базовых библиотек и основ Python;\r\n\r\nОпыт работы с Django для разработки коммерческих приложений (или с другими фреймворками: Pyramid, Flask, Fast API);\r\n\r\nПонимание REST-архитектуры, опыт разработки серверной части REST;\r\n\r\nПонимание ООП, знание паттернов проектирования;\r\n\r\nУверенная работа с git и другими инструментами разработчика.\r\nМЫ ПРЕДЛАГАЕМ:\r\n\r\nОфициальное оформление с первого дня выхода на работу;\r\nАтмосферу профессионального развития, вдохновленную принципами Agile;\r\nПрофессиональную команду девелоперов, авторитетных тимлидов и опытных наставников;\r\nУ нас самый уникальный портфель бенефитов по программе софинансирования (ДМС с стоматологией, фитнес, школа ин. языков на выбор, скидки на коробочные продукты банка и партнеров);\r\nМы поможем развить вашу проф. экспертизу: оплатим профессиональные тренинги и внешние образовательные курсы, участвуем в ИТ активностях (митапы, хакатоны, юконы);\r\nВовлеченность, комфорт, свобода, минимум бюрократии, нет дресс-кода, гибкое начало и завершение рабочего дня, приходи – с нами будет интересно!\r\nКлючевые навыки\r\nGit\r\nPython\r\nООП",
    "city": 2,
    "language": 2,
    "timestamp": "2022-06-16"
  }
}
]
